dikdik/__init__.py
dikdik/dict.py
dikdik/operations.py
dikdik/yaml.py
dikdik/yamlv2.py
dikdik-0.1.11.dist-info/LICENSE
dikdik-0.1.11.dist-info/METADATA
dikdik-0.1.11.dist-info/WHEEL
dikdik-0.1.11.dist-info/entry_points.txt
dikdik-0.1.11.dist-info/RECORD
