Metadata-Version: 2.1
Name: dikdik
Version: 0.1.11
Summary: dikdik - Common utils library
Home-page: https://github.com/mbovo/dikdik
License: LGPL-3.0-or-later
Author: Manuel Bovo
Author-email: manuel.bovo@gmail.com
Requires-Python: >=3.11,<4.0
Classifier: License :: OSI Approved :: GNU Lesser General Public License v3 or later (LGPLv3+)
Classifier: Programming Language :: Python :: 3
Classifier: Programming Language :: Python :: 3.11
Classifier: Programming Language :: Python :: 3.12
Requires-Dist: jsonschema (>=4.23.0,<5.0.0)
Requires-Dist: pyyaml (>=6.0,<7.0)
Requires-Dist: ruamel-yaml (>=0.18.6,<0.19.0)
Project-URL: Repository, https://github.com/mbovo/dikdik
